capblood_seq/__init__.py
capblood_seq/common.py
capblood_seq/dataset.py
capblood_seq/config/__init__.py
capblood_seq/config/config.py
capblood_seq/config/default.json
capblood_seq/resources/__init__.py
capblood_seq/resources/gene_pathway_dict.pickle
capblood_seq/resources/pathway_class_labels.tsv
capblood_seq/resources/pathway_classes.csv
capblood_seq-0.2.4.dist-info/DESCRIPTION.rst
capblood_seq-0.2.4.dist-info/METADATA
capblood_seq-0.2.4.dist-info/RECORD
capblood_seq-0.2.4.dist-info/WHEEL
capblood_seq-0.2.4.dist-info/metadata.json
capblood_seq-0.2.4.dist-info/top_level.txt
