Metadata-Version: 2.0
Name: capblood-seq
Version: 0.2.4
Summary: UNKNOWN
Home-page: https://github.com/thomsonlab/capblood-seq
Author: David Brown
Author-email: dibidave@gmail.com
License: UNKNOWN
Platform: UNKNOWN
Requires-Dist: pandas (>=0.23.0)
Requires-Dist: scrapi (>=0.5.1)
Requires-Dist: numpy
Requires-Dist: plotly
Requires-Dist: sklearn
Requires-Dist: scipy
Requires-Dist: statsmodels
Requires-Dist: matplotlib
Requires-Dist: pepars
